openmc_data_to_json/__init__.py
openmc_data_to_json/core.py
openmc_data_to_json-0.1.4.data/scripts/openmc-data-to-json
openmc_data_to_json-0.1.4.dist-info/LICENSE
openmc_data_to_json-0.1.4.dist-info/METADATA
openmc_data_to_json-0.1.4.dist-info/WHEEL
openmc_data_to_json-0.1.4.dist-info/top_level.txt
openmc_data_to_json-0.1.4.dist-info/zip-safe
openmc_data_to_json-0.1.4.dist-info/RECORD
