Metadata-Version: 2.1
Name: openmc-data-to-json
Version: 0.1.4
Summary: A tool for selectively extracting cross sections from OpenMC h5 files.
Home-page: https://github.com/openmc_data_storage/openmc_data_to_json
Author: Jonathan Shimwell
Author-email: mail@jshimwell.com
License: UNKNOWN
Platform: UNKNOWN
Requires-Dist: h5py
